funix_cloud/__init__.py
funix_cloud/api/__init__.py
funix_cloud/cli/__init__.py
funix_cloud/config/__init__.py
funix_cloud/key/__init__.py
funix_cloud/util/__init__.py
funix_cloud-0.1.2.dist-info/LICENSE.txt
funix_cloud-0.1.2.dist-info/METADATA
funix_cloud-0.1.2.dist-info/WHEEL
funix_cloud-0.1.2.dist-info/entry_points.txt
funix_cloud-0.1.2.dist-info/top_level.txt
funix_cloud-0.1.2.dist-info/RECORD
