Metadata-Version: 2.1
Name: funix-cloud
Version: 0.1.2
Summary: Funix cloud tool
Author-email: "Textea Inc." <bao@textea.co>
Project-URL: homepage, https://github.com/TexteaInc/funix-cloud
Keywords: funix,cloud
Classifier: Development Status :: 3 - Alpha
Classifier: Environment :: Console
Classifier: Environment :: Web Environment
Classifier: Intended Audience :: Developers
Classifier: License :: OSI Approved :: MIT License
Classifier: Programming Language :: Python :: 3.10
Classifier: Operating System :: OS Independent
Requires-Python: >=3.10
License-File: LICENSE.txt
Requires-Dist: requests >=2.31.0
Requires-Dist: fire >=0.5.0
Requires-Dist: rich >=13.5.2
Requires-Dist: qrcode >=7.4.2
Requires-Dist: python-dateutil >=2.8.2
Requires-Dist: tzlocal >=5.2
